MANIFEST.in
hr_payroll_data.xml
hr_payroll_demo.xml
hr_payroll_report.xml
hr_payroll_sequence.xml
hr_payroll_view.xml
hr_payroll_workflow.xml
res_config_view.xml
setup.py
./__init__.py
./__openerp__.py
./hr_payroll.py
./res_config.py
./report/__init__.py
./report/report_contribution_register.py
./report/report_payslip.py
./report/report_payslip_details.py
./wizard/__init__.py
./wizard/hr_payroll_contribution_register_report.py
./wizard/hr_payroll_payslips_by_employees.py
i18n/ar.po
i18n/bg.po
i18n/ca.po
i18n/cs.po
i18n/da.po
i18n/de.po
i18n/en_GB.po
i18n/es.po
i18n/es_CR.po
i18n/es_EC.po
i18n/es_MX.po
i18n/es_VE.po
i18n/et.po
i18n/fi.po
i18n/fr.po
i18n/gl.po
i18n/gu.po
i18n/he.po
i18n/hr.po
i18n/hr_payroll.pot
i18n/hu.po
i18n/id.po
i18n/it.po
i18n/ja.po
i18n/lo.po
i18n/lt.po
i18n/lv.po
i18n/mk.po
i18n/mn.po
i18n/nb.po
i18n/nl.po
i18n/pl.po
i18n/pt.po
i18n/pt_BR.po
i18n/ro.po
i18n/ru.po
i18n/sl.po
i18n/sr.po
i18n/sr@latin.po
i18n/sv.po
i18n/tr.po
i18n/vi.po
i18n/zh_CN.po
i18n/zh_TW.po
images/hr_company_contributions.jpeg
images/hr_employee_payslip.jpeg
images/hr_salary_heads.jpeg
images/hr_salary_structure.jpeg
openerp_hr_payroll.egg-info/PKG-INFO
openerp_hr_payroll.egg-info/SOURCES.txt
openerp_hr_payroll.egg-info/dependency_links.txt
openerp_hr_payroll.egg-info/requires.txt
openerp_hr_payroll.egg-info/top_level.txt
report/report_contribution_register.rml
report/report_contribution_register.sxw
report/report_payslip.rml
report/report_payslip.sxw
report/report_payslip_details.rml
report/report_payslip_details.sxw
security/hr_security.xml
security/ir.model.access.csv
static/src/img/icon.png
test/hr_payroll_report.yml
test/payslip.yml
wizard/hr_payroll_contribution_register_report.xml
wizard/hr_payroll_payslips_by_employees.xml